{
  "unversionedId": "overleaf/bibliography-styles/cje",
  "id": "overleaf/bibliography-styles/cje",
  "isDocsHomePage": false,
  "title": "How to use cje (economic) at Overleaf?",
  "description": "cje.bst has already been installed on the Overleaf servers and is ready for use. Thus, in order to use the file in question, simply define the style directly in your document: \\bibliographystyle The file extension .bst can be omitted.",
  "source": "@site/docs/overleaf/bibliography-styles/cje.md",
  "sourceDirName": "overleaf/bibliography-styles",
  "slug": "/overleaf/bibliography-styles/cje",
  "permalink": "/docs/overleaf/bibliography-styles/cje",
  "editUrl": "https://github.com/citedrive/bibtex.eu/docs/overleaf/bibliography-styles/cje.md",
  "version": "current",
  "sidebarPosition": 148,
  "frontMatter": {
    "sidebar_position": 148
  },
  "sidebar": "tutorialSidebar",
  "previous": {
    "title": "How to use ecta (economic) at Overleaf?",
    "permalink": "/docs/overleaf/bibliography-styles/ecta"
  },
  "next": {
    "title": "How to use jss2 (economic) at Overleaf?",
    "permalink": "/docs/overleaf/bibliography-styles/jss2"
  }
}