{
  "unversionedId": "overleaf/bibliography-styles/cell",
  "id": "overleaf/bibliography-styles/cell",
  "isDocsHomePage": false,
  "title": "How to use cell (cell) at Overleaf?",
  "description": "cell.bst has already been installed on the Overleaf servers and is ready for use. Thus, in order to use the file in question, simply define the style directly in your document: \\bibliographystyle The file extension .bst can be omitted.",
  "source": "@site/docs/overleaf/bibliography-styles/cell.md",
  "sourceDirName": "overleaf/bibliography-styles",
  "slug": "/overleaf/bibliography-styles/cell",
  "permalink": "/overleaf/bibliography-styles/cell",
  "editUrl": "https://github.com/citedrive/bibtex.eu/docs/overleaf/bibliography-styles/cell.md",
  "version": "current",
  "sidebarPosition": 93,
  "frontMatter": {
    "sidebar_position": 93
  },
  "sidebar": "tutorialSidebar",
  "previous": {
    "title": "How to use cascadilla (cascadilla) at Overleaf?",
    "permalink": "/overleaf/bibliography-styles/cascadilla"
  },
  "next": {
    "title": "How to use ChemCommun (chembst) at Overleaf?",
    "permalink": "/overleaf/bibliography-styles/ChemCommun"
  }
}