{
  "unversionedId": "overleaf/bibliography-styles/vancouver",
  "id": "overleaf/bibliography-styles/vancouver",
  "isDocsHomePage": false,
  "title": "How to use vancouver (vancouver) at Overleaf?",
  "description": "vancouver.bst has already been installed on the Overleaf servers and is ready for use. Thus, in order to use the file in question, simply define the style directly in your document: \\bibliographystyle The file extension .bst can be omitted.",
  "source": "@site/docs/overleaf/bibliography-styles/vancouver.md",
  "sourceDirName": "overleaf/bibliography-styles",
  "slug": "/overleaf/bibliography-styles/vancouver",
  "permalink": "/docs/overleaf/bibliography-styles/vancouver",
  "editUrl": "https://github.com/citedrive/bibtex.eu/docs/overleaf/bibliography-styles/vancouver.md",
  "version": "current",
  "sidebarPosition": 308,
  "frontMatter": {
    "sidebar_position": 308
  },
  "sidebar": "tutorialSidebar",
  "previous": {
    "title": "How to use vak (vak) at Overleaf?",
    "permalink": "/docs/overleaf/bibliography-styles/vak"
  }
}