{
  "unversionedId": "overleaf/bibliography-styles/email-html.",
  "id": "overleaf/bibliography-styles/email-html.",
  "isDocsHomePage": false,
  "title": "How to use email-html. (directory) at Overleaf?",
  "description": "email-html..bst has already been installed on the Overleaf servers and is ready for use. Thus, in order to use the file in question, simply define the style directly in your document: \\bibliographystyle{email-html.} The file extension .bst can be omitted.",
  "source": "@site/docs/overleaf/bibliography-styles/email-html..md",
  "sourceDirName": "overleaf/bibliography-styles",
  "slug": "/overleaf/bibliography-styles/email-html.",
  "permalink": "/docs/overleaf/bibliography-styles/email-html.",
  "editUrl": "https://github.com/citedrive/bibtex.eu/docs/overleaf/bibliography-styles/email-html..md",
  "version": "current",
  "sidebarPosition": 122,
  "frontMatter": {
    "sidebar_position": 122
  },
  "sidebar": "tutorialSidebar",
  "previous": {
    "title": "How to use address-vcard (directory) at Overleaf?",
    "permalink": "/docs/overleaf/bibliography-styles/address-vcard"
  },
  "next": {
    "title": "How to use address-html (directory) at Overleaf?",
    "permalink": "/docs/overleaf/bibliography-styles/address-html"
  }
}